streamlit_sortable_list/__init__.py
streamlit_sortable_list/frontend/dist/index.html
streamlit_sortable_list/frontend/dist/css/app.d6ec3624.css
streamlit_sortable_list/frontend/dist/js/app.05868a72.js
streamlit_sortable_list/frontend/dist/js/app.05868a72.js.map
streamlit_sortable_list/frontend/dist/js/chunk-vendors.e85fb313.js
streamlit_sortable_list/frontend/dist/js/chunk-vendors.e85fb313.js.map
streamlit_sortables_vue/__init__.py
streamlit_sortable_list-0.1.2.dist-info/LICENSE
streamlit_sortable_list-0.1.2.dist-info/METADATA
streamlit_sortable_list-0.1.2.dist-info/WHEEL
streamlit_sortable_list-0.1.2.dist-info/top_level.txt
streamlit_sortable_list-0.1.2.dist-info/RECORD
